msf_cli/__init__.py
msf_cli/broker.py
msf_cli/cli.py
msf_cli/devices.py
msf_cli/install.py
msf_cli/new.py
msf_cli/static/__init__.py
msf_cli/static/main.py
msf_cli/static/mpbridge.ignore
msf_cli/static/mqtt_as.json
msf_cli/static/settings.py
msf_cli-0.3.0.dist-info/METADATA
msf_cli-0.3.0.dist-info/WHEEL
msf_cli-0.3.0.dist-info/entry_points.txt
msf_cli-0.3.0.dist-info/RECORD
