Metadata-Version: 2.1
Name: msf-cli
Version: 0.3.0
Summary: 
Author: surdouski
Author-email: michael.surdouski@gmail.com
Requires-Python: >=3.10,<4.0
Classifier: Programming Language :: Python :: 3
Classifier: Programming Language :: Python :: 3.10
Classifier: Programming Language :: Python :: 3.11
Classifier: Programming Language :: Python :: 3.12
Requires-Dist: click (>=8.1.7,<9.0.0)
Requires-Dist: paho-mqtt (==1.6.1)
Requires-Dist: python-dotenv (>=1.0.1,<2.0.0)
Requires-Dist: rich (>=13.9.1,<14.0.0)
Requires-Dist: sniffs (>=0.6.2,<0.7.0)
